LICENCE.txt
MANIFEST.in
README.rst
setup.py
crispy_forms_foundation_demo/__init__.py
crispy_forms_foundation_demo/crispies.py
crispy_forms_foundation_demo/forms.py
crispy_forms_foundation_demo/models.py
crispy_forms_foundation_demo/urls.py
crispy_forms_foundation_demo/views.py
crispy_forms_foundation_demo.egg-info/PKG-INFO
crispy_forms_foundation_demo.egg-info/SOURCES.txt
crispy_forms_foundation_demo.egg-info/dependency_links.txt
crispy_forms_foundation_demo.egg-info/not-zip-safe
crispy_forms_foundation_demo.egg-info/requires.txt
crispy_forms_foundation_demo.egg-info/top_level.txt
crispy_forms_foundation_demo/templates/crispy_demo/accordions.html
crispy_forms_foundation_demo/templates/crispy_demo/base_forms.html
crispy_forms_foundation_demo/templates/crispy_demo/fieldsets.html
crispy_forms_foundation_demo/templates/crispy_demo/index.html
crispy_forms_foundation_demo/templates/crispy_demo/success.html
crispy_forms_foundation_demo/templates/crispy_demo/tabs.html