Metadata-Version: 1.1
Name: crispy-forms-foundation-demo
Version: 0.5.0
Summary: 
